LICENSE.txt
README.md
setup.cfg
setup.py
Topsis_Abhinav_102067004.egg-info/PKG-INFO
Topsis_Abhinav_102067004.egg-info/SOURCES.txt
Topsis_Abhinav_102067004.egg-info/dependency_links.txt
Topsis_Abhinav_102067004.egg-info/entry_points.txt
Topsis_Abhinav_102067004.egg-info/requires.txt
Topsis_Abhinav_102067004.egg-info/top_level.txt
topsis/__init__.py
topsis/topsis.py