Metadata-Version: 2.1
Name: Topsis-Abhinav-102067004
Version: 0.1.2
Summary: Implementation of topsis algorithm for multiple criteria decision making
Home-page: https://github.com/tyagi-abhinavv
Author: Abhinav Tyagi
Author-email: atyagi_be20@thapar.edu
Classifier: Operating System :: OS Independent
Classifier: License :: OSI Approved :: MIT License
Classifier: Programming Language :: Python :: 3.9
Classifier: Programming Language :: Python :: 3.10
Requires-Python: >=3.6
License-File: LICENSE.txt
